squarespace_commerce/Squarespace.py
squarespace_commerce/__init__.py
squarespace_commerce-0.1.9.dist-info/WHEEL
squarespace_commerce-0.1.9.dist-info/METADATA
squarespace_commerce-0.1.9.dist-info/RECORD
