Metadata-Version: 2.1
Name: squarespace-commerce
Version: 0.1.9
Summary: Pythonic access to the Squarespace Commerce API
Home-page: https://https://github.com/caseydierking/squarespace-commerce-python
License: MIT
Keywords: Squarespace,Commerce,Orders,Inventory,Transactions
Author: Casey Dierking
Author-email: casey@dierking.dev
Requires-Python: >=3.7,<4.0
Classifier: License :: OSI Approved :: MIT License
Classifier: Programming Language :: Python :: 3
Classifier: Programming Language :: Python :: 3.7
Classifier: Programming Language :: Python :: 3.8
Requires-Dist: requests (>=2.23.0,<3.0.0)
Project-URL: Repository, https://https://github.com/caseydierking/squarespace-commerce-python
